Metadata-Version: 2.1
Name: Codelock-CLI-dev
Version: 1.0.3
Summary: A cli for codelock development server
Home-page: UNKNOWN
Author: Codelock
License: MIT
Keywords: codelock,cli
Platform: UNKNOWN
Classifier: Development Status :: 2 - Pre-Alpha
Classifier: Intended Audience :: Developers
Classifier: Topic :: Utilities
Classifier: License :: OSI Approved :: MIT License
Classifier: Programming Language :: Python :: 3.7
Classifier: Programming Language :: Python :: 3.8
Classifier: Programming Language :: Python :: 3.9
Classifier: Programming Language :: Python :: 3.10
Provides-Extra: dev
License-File: LICENSE.txt
